binance_klines/__init__.py
binance_klines/cli.py
binance_klines/constants.py
binance_klines/downloader.py
binance_klines/utils.py
binance_klines-0.1.1.dist-info/LICENSE
binance_klines-0.1.1.dist-info/WHEEL
binance_klines-0.1.1.dist-info/entry_points.txt
binance_klines-0.1.1.dist-info/METADATA
binance_klines-0.1.1.dist-info/RECORD
