Metadata-Version: 2.1
Name: binance-klines
Version: 0.1.1
Summary: BinanceKlines - A tool to download OHLCV candlestick data (K-Lines) from Binance. Written in Python.
Author: Pierpaolo Pantone
Author-email: 24alsecondo@gmail.com
Requires-Python: >=3.10,<4.0
Classifier: Programming Language :: Python :: 3
Classifier: Programming Language :: Python :: 3.10
Classifier: Programming Language :: Python :: 3.11
Requires-Dist: ccxt (>=3.0.61,<4.0.0)
Requires-Dist: python-dotenv (>=1.0.0,<2.0.0)
Requires-Dist: pytz (>=2023.3,<2024.0)
